pypomes_scheduling/__init__.py
pypomes_scheduling/scheduling_pomes.py
pypomes_scheduling/threaded_scheduler.py
pypomes_scheduling-0.5.1.dist-info/METADATA
pypomes_scheduling-0.5.1.dist-info/WHEEL
pypomes_scheduling-0.5.1.dist-info/licenses/LICENSE
pypomes_scheduling-0.5.1.dist-info/RECORD
