Metadata-Version: 2.4
Name: pypomes_scheduling
Version: 0.5.1
Summary: A collection of Python pomes, penyeach (scheduling module)
Project-URL: Homepage, https://github.com/TheWiseCoder/PyPomes-Scheduling
Project-URL: Bug Tracker, https://github.com/TheWiseCoder/PyPomes-Scheduling/issues
Author-email: GT Nunes <wisecoder01@gmail.com>
License-File: LICENSE
Classifier: License :: OSI Approved :: MIT License
Classifier: Operating System :: OS Independent
Classifier: Programming Language :: Python :: 3
Requires-Python: >=3.14
Requires-Dist: apscheduler>=3.11.2
Requires-Dist: pypomes-core>=2.9.4
